smooai_logger/__init__.py
smooai_logger/aws_logger.py
smooai_logger/logger.py
smooai_logger/py.typed
smooai_logger/socketio_logger_adapter.py
smooai_logger/uvicorn_logger_adapter.py
smooai_logger/utils/__init__.py
smooai_logger/utils/date.py
smooai_logger/utils/json.py
smooai_logger-3.1.2.dist-info/METADATA
smooai_logger-3.1.2.dist-info/WHEEL
smooai_logger-3.1.2.dist-info/RECORD
