Metadata-Version: 2.4
Name: smooai-logger
Version: 3.1.2
Summary: Context-aware structured logging utilities for Python that mirror the @smooai/logger toolkit.
Project-URL: Homepage, https://github.com/SmooAI/logger
Project-URL: Repository, https://github.com/SmooAI/logger
Project-URL: Issues, https://github.com/SmooAI/logger/issues
Author-email: SmooAI <brent@smooai.com>
License: MIT
Keywords: aws,logging,observability,smooai,structured-logging
Classifier: License :: OSI Approved :: MIT License
Classifier: Operating System :: OS Independent
Classifier: Programming Language :: Python
Classifier: Programming Language :: Python :: 3
Classifier: Programming Language :: Python :: 3.12
Requires-Python: >=3.12
Requires-Dist: colorist>=1.5.2
Requires-Dist: pendulum>=3.0.0
Requires-Dist: pydantic-extra-types>=2.0.0
Requires-Dist: pydantic>=2.7.0
Requires-Dist: rich>=13.0.0
